MANIFEST.in
README.rst
setup.cfg
setup.py
socialshare/__init__.py
socialshare/share.py
socialshare.egg-info/PKG-INFO
socialshare.egg-info/SOURCES.txt
socialshare.egg-info/dependency_links.txt
socialshare.egg-info/not-zip-safe
socialshare.egg-info/requires.txt
socialshare.egg-info/top_level.txt