Metadata-Version: 1.1
Name: socialshare
Version: 0.1.3
Summary: social share is package for share contents on social media networks.
Home-page: https://github.com/renjith-tring/socialshare
Author: Renjith S Raj
Author-email: renjith.r@tringapps.com
License: MIT
Keywords: django,social,share
Platform: UNKNOWN
Classifier: Development Status :: 3 - Alpha
Classifier: Topic :: Internet
Classifier: License :: OSI Approved :: MIT License
Classifier: Intended Audience :: Developers
Classifier: Environment :: Web Environment
Classifier: Programming Language :: Python
Classifier: Programming Language :: Python :: 2.6
Classifier: Programming Language :: Python :: 2.7
Classifier: Programming Language :: Python :: 3
